spotdlfork
